rplc/bin/__init__.py
rplc/bin/cli.py
rplc/lib/__init__.py
rplc/lib/config.py
rplc/lib/discovery.py
rplc/lib/domain.py
rplc/lib/mirror.py
rplc-0.8.0.dist-info/licenses/LICENSE
rplc-0.8.0.dist-info/METADATA
rplc-0.8.0.dist-info/WHEEL
rplc-0.8.0.dist-info/entry_points.txt
rplc-0.8.0.dist-info/top_level.txt
rplc-0.8.0.dist-info/RECORD
