Metadata-Version: 2.4
Name: rplc
Version: 0.8.0
Summary: Add your description here
Author-email: sysid <sysid@gmx.de>
Requires-Python: >=3.12
License-File: LICENSE
Requires-Dist: typer>=0.15.1
Dynamic: license-file
